{
  "bc95f3ef7db4dea33e6e99c9b8385a21ce82dec4.png": {
    "title": "MCCCmapBW.png",
    "description": "Black and White Unmarked Map",
    "tags": []
  },
  "9f5318c3c56d810d64bac676ade2145213f7355a.png": {
    "title": "mcccflag.png",
    "description": "flag pin",
    "tags": []
  },
  "aa8bff76ac607eb623792dc7413667875cf25e3c.mp4": {
    "title": "MCCCvideointro.mp4",
    "description": "final;\r\n",
    "tags": []
  },
  "17f7d956bdb47d6e8f0098092561327c8939345f.gif": {
    "title": "MCCatHappy.gif",
    "description": "all done good",
    "tags": []
  },
  "365a256b3ce1420a864221a5e37bf9733919a24f.png": {
    "title": "MW2.png",
    "description": "mw2\r\n",
    "tags": []
  },
  "1bc9b1ef0de4d7502367facddcead9c3320c2a85.gif": {
    "title": "pool.gif",
    "description": "Pool",
    "tags": []
  },
  "89fa3dcc72d7e58a0a3f961bc7977398fa3573cb.gif": {
    "title": "ad2.gif",
    "description": "Administrative Services Building",
    "tags": []
  }
}